ltd_mason-0.2.5.dist-info/DESCRIPTION.rst
ltd_mason-0.2.5.dist-info/METADATA
ltd_mason-0.2.5.dist-info/RECORD
ltd_mason-0.2.5.dist-info/WHEEL
ltd_mason-0.2.5.dist-info/entry_points.txt
ltd_mason-0.2.5.dist-info/metadata.json
ltd_mason-0.2.5.dist-info/top_level.txt
ltdmason/__init__.py
ltdmason/_version.py
ltdmason/cli.py
ltdmason/manifest.py
ltdmason/product.py
ltdmason/redirectdircli.py
ltdmason/s3upload.py
ltdmason/traviscli.py
ltdmason/uploader.py
