Metadata-Version: 1.1
Name: ltd-mason
Version: 0.2.5
Summary: LSST the Docs build tool
Home-page: https://github.com/lsst-sqre/ltd-mason
Author: Jonathan Sick
Author-email: jsick@lsst.org
License: MIT
Keywords: lsst
Platform: UNKNOWN
Classifier: Development Status :: 4 - Beta
Classifier: License :: OSI Approved :: MIT License
Classifier: Programming Language :: Python :: 2.7
Classifier: Programming Language :: Python :: 3.4
Classifier: Programming Language :: Python :: 3.5
